anime_autodownloader/__init__.py
anime_autodownloader/downloader.py
anime_autodownloader/navigator.py
anime_autodownloader/utils.py
anime_autodownloader-0.0.3.dist-info/LICENSE
anime_autodownloader-0.0.3.dist-info/WHEEL
anime_autodownloader-0.0.3.dist-info/METADATA
anime_autodownloader-0.0.3.dist-info/RECORD
